{
    "modifiedTime": "2025-09-29T19:08:57.000Z",
    "subCategory": null,
    "statusType": "Closed",
    "subject": "Escalación de Silver-AI (Prueba de Integración)",
    "dueDate": null,
    "departmentId": "504200000001777045",
    "channel": "Whatsapp",
    "onholdTime": null,
    "language": "Spanish",
    "source": {
        "appName": null,
        "extId": null,
        "permalink": null,
        "type": "SYSTEM",
        "uuid": null,
        "appPhotoURL": null
    },
    "resolution": null,
    "sharedDepartments": [],
    "closedTime": "2025-09-29T19:08:58.000Z",
    "approvalCount": "0",
    "isOverDue": false,
    "isTrashed": false,
    "createdTime": "2025-09-29T19:08:57.000Z",
    "id": "504200000057372001",
    "isResponseOverdue": false,
    "customerResponseTime": "2025-09-29T19:08:57.000Z",
    "productId": null,
    "contactId": "504200000057058079",
    "threadCount": "1",
    "secondaryContacts": [],
    "priority": null,
    "classification": null,
    "commentCount": "0",
    "taskCount": "0",
    "accountId": null,
    "phone": "62587119",
    "webUrl": "https://desk.zoho.com/support/soporteclientes/ShowHomePage.do#Cases/dv/504200000057372001",
    "isSpam": false,
    "status": "Closed",
    "entitySkills": [],
    "ticketNumber": "52312",
    "customFields": {
        "Reportar un problema": null,
        "Correo electrónico de contacto": null,
        "Fecha Hora de publicación": null,
        "Solicitud - Moovers": null,
        "Vacaciones": "false",
        "Nombre del responsable": null,
        "Tipo de solicitud de Cliente ": null,
        "Fecha inicio": null,
        "Servicio en activo ": null,
        "Tipo de problema Otro": null,
        "Perfil de cliente": null,
        "Tipo de cargo adicional": null,
        "Por Favor adjunte la boleta de vacaciones": "false",
        "HOLLAAA": null,
        "Tipo de incidencia:": null,
        "Puesto que se desea cubrir": null,
        "Cliente - nombre comercial": null,
        "Habilitar COD": null,
        "Desde": null,
        "Solicitud - Delegados": null,
        "Elija el servicio contratado": null,
        "Cédula de la persona física o jurídica": null,
        "Tipo de Facturación": null,
        "Tipo de servicio ": null,
        "Moover": null,
        "Incidencia de cobro contra entrega en: ": null,
        "Nombre de la persona que hará uso del equipo": null,
        "IBAN": null,
        "Acceso directo Moover CS": null,
        "¿Tiene crédito? ": null,
        "Nombre del colaborador": null,
        "Comentarios adicionales": null,
        "Posición en la empresa": null,
        "Selecciona si requiere comunicado": null,
        "Tareas que se deben parametrizar": null,
        "Reembolso": null,
        "Describe otras necesidades": null,
        "Cantidad": null,
        "Ruta": null,
        "¿Fue impartida la capacitación?": null,
        "Compra": null,
        "Selecciona una de las opciones": null,
        "Tipo de problema en el cobro": null,
        "Monto de factura": null,
        "Cargo": null,
        "Solicitud - Clientes": null,
        "Facturas": null,
        "Plantilla": null,
        "Día de disfrute": null,
        "Tipo de solicitud a nivel Interno": null,
        "Tipo de incorporación": null,
        "Problema ": null,
        "Nueva fecha solicitada": null,
        "Tipo de servicio : ": null,
        "Retorno": "false",
        "¿Debe añadirse al listado de documentos oficiales?": null,
        "Descripción de la cancelación": null,
        "Monto del cargo adicional.": null,
        "Motivo del cambio": null,
        "Envío ": null,
        "Fecha": null,
        "Escoja la semana que se efectuó la gestión": null,
        "URL del ecommerce": null,
        "Teléfono Usuario": null,
        "Escalar ": null,
        "Razón Social Cliente": null,
        "Lugar donde ocurrió la incidencia": null,
        "Punto donde se produce la incidencia cobro": null,
        "Express": null,
        "Decimal 1": null,
        "¿Requiere capacitación?": null,
        "Tipo de ticket": null,
        "Trigger assignment rule": "false",
        "Configurar tarifas": null,
        "Fecha y hora de expiración": null,
        "Incidencia en tiempo de espera": null,
        "Crear usuarios": "false",
        "ID del Envío": null,
        "Equipo": null,
        "Solicitudes hacia Desarrollo": null,
        "Mi paquete se envía por Moovin": "false",
        "Agregar enlace  al CRM": null,
        "Datos": null,
        "Cantidad de vacantes": null,
        "Configurar Cobro contra entrega": null,
        "¿Tiene desarrollador?": null,
        "Dirección completa": null,
        "Monto a rebajar al responsable BORRAR": null,
        "Justifica la prioridad del ticket": null,
        "Explicar tipo de problema": null,
        "URL Carta autorización de rebajo": null,
        "Punto donde se debe ajustar el tiempo de espera": null,
        "Origen": null,
        "Nombre físico ó jurídico completo": null,
        "ID perfil integrado": null,
        "Seleccione el tipo gestión": null,
        "Perfil / Perfiles": null,
        "Actualizado en Backend": "false",
        "Monto a facturar IVA no incluido": null,
        "Perfil / Perfiles:": null,
        "Comprobante cargo adicional": null,
        "Monto de la factura": null,
        "Precio": null,
        "Justifica la necesidad de incorporación.": null,
        "Ingrese las herramientas donde requiere crear": null,
        "Consultar": null,
        "Ingrese usuarios necesarios ": null,
        "Selecciona equipos necesarios ": null,
        "Elija el  afiliado": null,
        "Devolver a ": null,
        "Tipo de ticket - integración": null,
        "Acceso directo Usuario CS": null,
        "Selecciona el tipo de Ticket": null,
        "Día de cumpleaños": "false",
        "Gestión de crédito": null,
        "Hay un responsable de la incidencia?": null,
        "Otros cargos": null,
        "Escalar a:": null,
        "En qué proceso de la bodega ocurrio": null,
        "Fecha de incorporación deseada": null,
        "¿En qué podemos ayudarte?": null,
        "Fecha fin": null,
        "Monto a abonar al cliente.": null,
        "Nombre de contacto": null,
        "Etiquetas de búsqueda": null,
        "Minutos reales en el punto": null,
        "Eliminar usuarios": "false",
        "Configurar Tarifa": null,
        "Necesidades de equipamiento": null,
        "Crear retorno": "false",
        "Monto a abonar al cliente": null,
        "Impuestos": null,
        "Date 1": null,
        "Hay un responsable?": null,
        "Adjunto la boleta de Vacaciones?": "true",
        "Trigger assignment rule.": "false",
        "Número de factura": null,
        "Causa de la incidencia en tiempos de espera": null,
        "Tipo de servicio.": null,
        "País": null,
        "Monto del cargo adicional": null,
        "Dónde se debe ajustar?": null,
        "Perfil del Cliente": null,
        "ID de Express AAAA": null,
        "Url comprobante de la transacción": null,
        "Cargo que ocupará": null,
        "Equipo a cambiar": null,
        "La incorporación ha sido aprobada por la Gerencia": "false",
        "Número de paquete o servicio": null,
        "Nombre de empresa": null,
        "Describe que problema resuelve": null,
        "Modificar": "false",
        "Teléfono Moover": null,
        "¿Usa Fulfillment?": null,
        "Departamento": null,
        "Fecha de entrega": null,
        "Acción correctiva": null,
        "Tipo de servicios afectado: ": null,
        "Correo electrónico": null,
        "Seguimiento - Tiempo": null,
        "Herramienta de uso": null,
        "Servicio": null,
        "Monto a rebajar al responsable": null,
        "Seguimiento - Fase": null,
        "Cúales son las ventajas": null,
        "Punto donde se produce la incidencia de cobro ": null,
        "Fecha de cumpleaños": null
    },
    "isArchived": false,
    "description": "ESTO ES UNA PRUEBA, por favor hacer caso omiso.\n\nUsuario afirma tener artículos que requieren ser recogidos pero no conoce el número de seguimiento o información del paquete.",
    "timeEntryCount": "0",
    "channelRelatedInfo": null,
    "responseDueDate": null,
    "isDeleted": false,
    "modifiedBy": "504200000000138033",
    "email": null,
    "layoutDetails": {
        "id": "504200000037719616",
        "layoutName": "Solicitud Receptores"
    },
    "channelCode": null,
    "cf": {
        "cf_telefono_moover": null,
        "cf_fecha_de_cumpleanos": null,
        "cf_compra": null,
        "cf_solicitud_clientes": null,
        "cf_perfil_perfiles": null,
        "cf_crear_retorno": "false",
        "cf_id_del_envio": null,
        "cf_lista_de_seleccion_1_1": null,
        "cf_en_que_podemos_ayudarte": null,
        "cf_dia_de_cumpleanos": "false",
        "cf_causa_de_la_incidencia_en_tiempos_de_espera": null,
        "cf_nombre_del_colaborador_que_solicita_las_vacaciones": null,
        "cf_fecha_de_entrega": null,
        "cf_perfil_de_cliente": null,
        "cf_tipo": null,
        "cf_pretension": null,
        "cf_fecha": null,
        "cf_periodo_a_facturar": null,
        "cf_cuales_son_las_ventajas": null,
        "cf_solicitud_delegados": null,
        "cf_tipo_de_servicio_2": null,
        "cf_tipo_de_servicio_3": null,
        "cf_id_de_express": null,
        "cf_tipo_de_ticket_integracion": null,
        "cf_tipo_de_servicio_1": null,
        "cf_agregar_tareas_al_agregador": null,
        "cf_etiqueta": null,
        "cf_id_de_envio": null,
        "cf_tipo_de_envio": null,
        "cf_trigger_assignment_rule": "false",
        "cf_otros_cargos": null,
        "cf_tipo_de_problema_otro": null,
        "cf_id_cliente": null,
        "cf_devolver_a": null,
        "cf_incidencia": null,
        "cf_punto_donde_se_produce_la_incidencia_de_cobro": null,
        "cf_tipo_de_contrato": null,
        "cf_habilitar_cod": null,
        "cf_seleccion_multiple_1": null,
        "cf_incidencia_de_cobro_contra_entrega_en": null,
        "cf_comentarios_adicionales": null,
        "cf_cedula_juridica_cliente": null,
        "cf_solicitud_moovers": null,
        "cf_moover": null,
        "cf_monto_en_dispuata": null,
        "cf_datos": null,
        "cf_correo_electronico_de_contacto": null,
        "cf_id_envio": null,
        "cf_seguimiento_tiempo": null,
        "cf_punto_que_se_debe_ajustar": null,
        "cf_solicitud_interno": null,
        "cf_acceso_directo_paquete_servicio_orden": null,
        "cf_descripcion_de_la_version_del_moover": null,
        "cf_correo_electronico_confirmacion_de_transaccion": null,
        "cf_en_que_proceso_de_la_bodega_ocurrio": null,
        "cf_vacaciones": "false",
        "cf_acceso_directo_usuario_cs": null,
        "cf_necesito_ayuda_con": null,
        "cf_servicio_en_activo": null,
        "cf_tipo_de_solicitud_de_cliente": null,
        "cf_configurar_tarifa": null,
        "cf_envio": null,
        "cf_detalles": null,
        "cf_escalar": null,
        "cf_punto_donde_se_ajusto_tiempo_de_espera": null,
        "cf_etidad_bancaria": null,
        "cf_fecha_fin": null,
        "cf_nombre_del_usuario": null,
        "cf_url_manual_de_la_funcionalidad": null,
        "cf_tipo_de_cargo_adicional": null,
        "cf_terminal": null,
        "cf_escoje_donde_requieres_usuarios": null,
        "cf_describe_que_problema_resuelve": null,
        "cf_comprobante_cargo_adicional": null,
        "cf_fecha_y_hora_de_expiracion": null,
        "cf_cargo": null,
        "cf_selecciona_equipos_necesarios": null,
        "cf_plantilla": null,
        "cf_hollaaa": null,
        "cf_fecha_de_servicio": null,
        "cf_fecha_de_inicio_prevista": null,
        "cf_trigger_assignment_rule_1": "false",
        "cf_adjunto_la_boleta_de_vacaciones": "true",
        "cf_tipo_de_servicio": null,
        "cf_hay_un_reponsable_claro_de_la_incidencia_con_el_pa": null,
        "cf_equipamiento": null,
        "cf_numero_de_factura": null,
        "cf_comunicate_con_nuestro_equipo": null,
        "cf_perfil_de_cliente_1": null,
        "cf_numero_de_cuenta": null,
        "cf_nombre_de_colaborador": null,
        "cf_origen": null,
        "cf_fecha_hora_de_publicacion": null,
        "cf_ver_info_del_moover": null,
        "cf_requiere_capacitacion": null,
        "cf_cantidad_de_vacantes": null,
        "cf_precio": null,
        "cf_nombre_de_cliente": null,
        "cf_slecciona_segun_corresponda": null,
        "cf_reembolso": null,
        "cf_tipo_de_solicitante": null,
        "cf_cliente": null,
        "cf_retorno": "false",
        "cf_tipo_de_servicios_afectado": null,
        "cf_express": null,
        "cf_nombre_de_contacto": null,
        "cf_crear_usuarios": "false",
        "cf_actualizado_en_backend": "false",
        "cf_desde": null,
        "cf_impuestos": null,
        "cf_perfil_perfiles_1": null,
        "cf_configurar_cod": null,
        "cf_explicar_tipo_de_problema": null,
        "cf_por_favor_adjunte_la_boleta_de_vacaciones": "false",
        "cf_motivo_del_cambio": null,
        "cf_departamento": null,
        "cf_user_para": null,
        "cf_dia_de_disd_frute": null,
        "cf_razon_social_cliente": null,
        "cf_lista_de_seleccion_1": null,
        "cf_accion_correctiva": null,
        "cf_escalar_a": null,
        "cf_monto_a_facturar": null,
        "cf_esta_aprobada_la_contratacion": "false",
        "cf_facturas": null,
        "cf_mi_paquete_se_envia_por_moovin": "false",
        "cf_tiene_credito": null,
        "cf_titular_de_la_cuenta": null,
        "cf_enlace_al_perfil_de_puesto": null,
        "cf_monto_de_factura": null,
        "cf_nombre_de_empresa": null,
        "cf_id_servicios_afectado": null,
        "cf_configurar_tarifas": null,
        "cf_cantidad": null,
        "cf_modificar": "false",
        "cf_tipo_1": null,
        "cf_tipo_de_incidencia": null,
        "cf_elija": null,
        "cf_total_monto": null,
        "cf_puesto": null,
        "cf_tipo_de_problema": null,
        "cf_problema": null,
        "cf_puesto_a_cubrir": null,
        "cf_tipo_de_tictek": null,
        "cf_minutos_reales_en_el_punto": null,
        "cf_activar_credito": null,
        "cf_monto_del_cargo_adicional": null,
        "cf_causa_del_problema": null,
        "cf_iban": null,
        "cf_lugar_donde_ocurrio_la_incidencia": null,
        "cf_describe_otras_necesidades": null,
        "cf_acceso_directo_info_cliente": null,
        "cf_date_1": null,
        "cf_decimal_1": null,
        "cf_incidencia_en_tiempo_de_espera": null,
        "cf_seleccion_multiple_1_1": null,
        "cf_seleccion_multiple_1_2": null,
        "cf_eliminar_usuarios": "false",
        "cf_telefono_usuario": null,
        "cf_tipo_de_cuenta": null,
        "cf_tipo_de_incidencia_1": null,
        "cf_descripcion_de_lo_sucedido_con_el_paquete": null,
        "cf_nueva_fecha_solicitada": null,
        "cf_ingrese_usuarios_necesarios": null,
        "cf_multiselect_1": null,
        "cf_seguimiento": null,
        "cf_fecha_inicio": null
    },
    "slaId": null,
    "layoutId": "504200000037719616",
    "assigneeId": null,
    "teamId": "504200000035799001",
    "attachmentCount": "0",
    "isEscalated": false,
    "category": null
}